doodle/__init__.py
doodle/__main__.py
doodle/data.py
flasknoodle-1.0.5.dist-info/LICENSE
flasknoodle-1.0.5.dist-info/METADATA
flasknoodle-1.0.5.dist-info/WHEEL
flasknoodle-1.0.5.dist-info/entry_points.txt
flasknoodle-1.0.5.dist-info/top_level.txt
flasknoodle-1.0.5.dist-info/RECORD
