Metadata-Version: 2.1
Name: flasknoodle
Version: 1.0.5
Summary: flask project generator
Home-page: https://github.com/odunet/Flask_ProjectGenerator
Author: Ayokunle Odutayo
Author-email: odunet2000@yahoo.com
License: MIT
Platform: UNKNOWN
Classifier: License :: OSI Approved :: MIT License
Classifier: Programming Language :: Python :: 3.6
Classifier: Programming Language :: Python :: 3.7
Classifier: Programming Language :: Python :: 3.8
